[
  {
    "nome": "Sevdaliza",
    "sobre": "Sevdaliza",
    "sobre-idioma": "en",
    "embed": '<iframe width="560" height="315" src="https://www.youtube.com/embed/9t7SclAXoQw" frameborder="0" allowfullscreen></iframe>',
    "link": "https://open.spotify.com/artist/5MraexJKZDrQYzS98kNwie"
  },
  {
    "nome": "Kendrick Lamar",
    "sobre": 'Kendrick Lamar',
    "sobre-idioma": "pt",
    "embed": '<iframe width="560" height="315" src="https://www.youtube.com/embed/NLZRYQMLDW4" frameborder="0" allowfullscreen></iframe>',
    "link": "https://open.spotify.com/artist/2YZyLoL8N0Wb9xBt1NhZWg"
  },
  {
    "nome": "Jaden Smith",
    "sobre": "Jaden Smith",
    "sobre-idioma": "pt",
    "embed": '<iframe width="560" height="315" src="https://www.youtube.com/embed/Fof9lHaApXc" frameborder="0" allowfullscreen></iframe>',
    "link": ""
  },
  {
    "nome": "SZA",
    "sobre": "SZA (singer)",
    "sobre-idioma": "en",
    "embed": '<iframe width="560" height="315" src="https://www.youtube.com/embed/ITZXgn81uyk?rel=0&amp;showinfo=0" frameborder="0" allowfullscreen></iframe>',
    "link": "https://www.youtube.com/results?search_query=sza"
  },
  {
    "nome": "Willow Smith",
    "sobre": "Willow Smith",
    "sobre-idioma": "pt",
    "embed": '<iframe width="560" height="315" src="https://www.youtube.com/embed/YXL4GagVBZs" frameborder="0" allowfullscreen></iframe>',
    "link": "https://open.spotify.com/artist/3rWZHrfrsPBxVy692yAIxF"
  }
]